testweaver/__init__.py
testweaver/constants.py
testweaver/functions.py
testweaver-1.0.0.283.dist-info/METADATA
testweaver-1.0.0.283.dist-info/WHEEL
testweaver-1.0.0.283.dist-info/top_level.txt
testweaver-1.0.0.283.dist-info/RECORD
